pysj/__init__.py
pysj/crypto.py
pysj/exjson.py
pysj/formats.py
pysj/main.py
pysj/ndjson.py
pysj-1.1.1.dist-info/LICENSE
pysj-1.1.1.dist-info/WHEEL
pysj-1.1.1.dist-info/METADATA
pysj-1.1.1.dist-info/RECORD
