Metadata-Version: 2.1
Name: pysj
Version: 1.1.1
Summary: Pysj makes Python development more comfortable, with utils, classes and helper
Author: Sondre S. Ødegård
Requires-Python: >=3.10
Classifier: License :: OSI Approved :: MIT License
Classifier: Topic :: Software Development
Requires-Dist: black ; extra == "dev"
Requires-Dist: isort ; extra == "dev"
Requires-Dist: hypothesis[cli] ; extra == "dev"
Requires-Dist: pytest ; extra == "dev"
Requires-Dist: pytest-cov ; extra == "dev"
Requires-Dist: coverage ; extra == "dev"
Requires-Dist: numpy ; extra == "dev"
Requires-Dist: tox ; extra == "dev"
Requires-Dist: flit ; extra == "dev"
Project-URL: Documentation, https://github.com/sondreod/pysj
Project-URL: Source, https://github.com/sondreod/pysj
Provides-Extra: dev
